verilog_ALU/RTL Design/ALU_pipe_line.v
module pipe_line(Zout, rs1, rs2, rd, func, addr, clk1, clk2);

    input [3:0] rs1, rs2, rd, func;
    input [7:0] addr;
    input clk1, clk2;               // Two-phase clock
    output [15:0] Zout;

    reg [15:0] L12_A, L12_B, L23_Z, L34_Z;
    reg [3:0]  L12_rd, L12_func, L23_rd;
    reg [7:0]  L12_addr, L23_addr, L34_addr;

    reg [15:0] regbank [0:15];      // Register bank
    reg [15:0] mem [0:255];         // 256 x 16 memory

    assign Zout = L34_Z;

    always @(posedge clk1)
    begin 
        L12_A       <=  #2  regbank[rs1];
        L12_B       <=  #2  regbank[rs2];
        L12_rd      <=  #2  rd;
        L12_func    <=  #2  func;
        L12_addr    <=  #2  addr;       // ** stage 1 **
    end

    always @(negedge clk2)
    begin
        case (L12_func)
            0:  L23_Z   <=  #2  L12_A + L12_B;
            1:  L23_Z   <=  #2  L12_A - L12_B;
            2:  L23_Z   <=  #2  L12_A * L12_B;
            3:  L23_Z   <=  #2  L12_A;
            4:  L23_Z   <=  #2  L12_B;
            5:  L23_Z   <=  #2  L12_A & L12_B;
            6:  L23_Z   <=  #2  L12_A | L12_B;
            7:  L23_Z   <=  #2  L12_A ^ L12_B;
            8:  L23_Z   <=  #2  - L12_A;
            9:  L23_Z   <=  #2  - L12_B;
           10:  L23_Z   <=  #2  L12_A >> 1;
           11:  L23_Z   <=  #2  L12_A << 1;
            default: L23_Z <= #2 16'hxxxx;
        endcase
        L23_rd      <=  #2  L12_rd;
        L23_addr    <=  #2  L12_addr;       // ** STAGE 2 **
    end
    
    always @(posedge clk1)
    begin
        regbank[L23_rd] <=  #2 L23_Z;
        L34_Z           <=  #2 L23_Z;
        L34_addr        <=  #2 L23_addr;    // ** STAGE 3 **
    end

    always @(posedge clk2)
    begin
        mem[L34_addr]   <=  #2 L34_Z;       // ** STAGE 4 **
    end

endmodule

verilog_ALU/Test Benches/alu_pl_tb1.v

module pipeline_test;

    // Inputs
    reg [3:0] rs1, rs2, rd, func;
    reg [7:0] addr;
    reg clk1, clk2;

    // Output
    wire [15:0] Zout;

    // Instantiate DUT
    pipe_line DUT (
        .Zout(Zout),
        .rs1(rs1),
        .rs2(rs2),
        .rd(rd),
        .func(func),
        .addr(addr),
        .clk1(clk1),
        .clk2(clk2)
    );

    //---------------------------------------------------------
    // Clock Generation
    //---------------------------------------------------------

    initial begin
        clk1 = 0;
        forever #10 clk1 = ~clk1;
    end

    initial begin
        clk2 = 0;
        #5;
        forever #10 clk2 = ~clk2;
    end

    //---------------------------------------------------------
    // Initialize Register Bank
    //---------------------------------------------------------

    integer i;

    initial begin

        for(i=0;i<16;i=i+1)
            DUT.regbank[i] = 0;

        DUT.regbank[0] = 16'd10;
        DUT.regbank[1] = 16'd20;
        DUT.regbank[2] = 16'd5;
        DUT.regbank[3] = 16'd4;
        DUT.regbank[4] = 16'd15;
        DUT.regbank[5] = 16'd8;

    end

    //---------------------------------------------------------
    // Apply Instructions
    //---------------------------------------------------------

    initial begin

        rs1 = 0;
        rs2 = 0;
        rd  = 0;
        func = 0;
        addr = 0;

        #20;

        //-------------------------------------------------
        // R6 = R0 + R1 = 10 + 20 = 30
        //-------------------------------------------------
        rs1 = 0;
        rs2 = 1;
        rd  = 6;
        func = 0;
        addr = 8'h10;

        #20;

        //-------------------------------------------------
        // R7 = R1 - R2 = 20 - 5 = 15
        //-------------------------------------------------
        rs1 = 1;
        rs2 = 2;
        rd  = 7;
        func = 1;
        addr = 8'h11;

        #20;

        //-------------------------------------------------
        // R8 = R2 * R3 = 5 * 4 = 20
        //-------------------------------------------------
        rs1 = 2;
        rs2 = 3;
        rd  = 8;
        func = 2;
        addr = 8'h12;

        #20;

        //-------------------------------------------------
        // R9 = R4 AND R5 = 15 & 8 = 8
        //-------------------------------------------------
        rs1 = 4;
        rs2 = 5;
        rd  = 9;
        func = 5;
        addr = 8'h13;

        #20;

        //-------------------------------------------------
        // R10 = R4 OR R5 = 15 | 8 = 15
        //-------------------------------------------------
        rs1 = 4;
        rs2 = 5;
        rd  = 10;
        func = 6;
        addr = 8'h14;

        #20;

        //-------------------------------------------------
        // R11 = R4 XOR R5 = 15 ^ 8 = 7
        //-------------------------------------------------
        rs1 = 4;
        rs2 = 5;
        rd  = 11;
        func = 7;
        addr = 8'h15;

        #20;

        //-------------------------------------------------
        // R12 = -R2 = -5
        //-------------------------------------------------
        rs1 = 2;
        rs2 = 0;
        rd  = 12;
        func = 8;
        addr = 8'h16;

        #20;

        //-------------------------------------------------
        // R13 = R4 >> 1 = 15 >> 1 = 7
        //-------------------------------------------------
        rs1 = 4;
        rs2 = 0;
        rd  = 13;
        func = 10;
        addr = 8'h17;

        #20;

        //-------------------------------------------------
        // R14 = R2 << 1 = 5 << 1 = 10
        //-------------------------------------------------
        rs1 = 2;
        rs2 = 0;
        rd  = 14;
        func = 11;
        addr = 8'h18;

        #100;

        $finish;

    end

    //---------------------------------------------------------
    // Monitor
    //---------------------------------------------------------

    initial begin

        $dumpfile("pipeline.vcd");
        $dumpvars(0,pipeline_test);

        $display("------------------------------------------------------------");
        $display("Time\tFunc\tRS1\tRS2\tRD\tZout");
        $display("------------------------------------------------------------");

        $monitor("%0t\t%d\t%d\t%d\t%d\t%d",
                 $time, func, rs1, rs2, rd, Zout);

    end

endmodule

verilog_ALU/Waveforms/pipeline.vcd
$date
	Wed Jul 08 23:17:40 2026
$end
$version
	Icarus Verilog
$end
$timescale
	1s
$end
$scope module pipeline_test $end
$var wire 16 ! Zout [15:0] $end
$var reg 8 " addr [7:0] $end
$var reg 1 # clk1 $end
$var reg 1 $ clk2 $end
$var reg 4 % func [3:0] $end
$var reg 4 & rd [3:0] $end
$var reg 4 ' rs1 [3:0] $end
$var reg 4 ( rs2 [3:0] $end
$var integer 32 ) i [31:0] $end
$scope module DUT $end
$var wire 16 * Zout [15:0] $end
$var wire 8 + addr [7:0] $end
$var wire 1 # clk1 $end
$var wire 1 $ clk2 $end
$var wire 4 , func [3:0] $end
$var wire 4 - rd [3:0] $end
$var wire 4 . rs1 [3:0] $end
$var wire 4 / rs2 [3:0] $end
$var reg 16 0 L12_A [15:0] $end
$var reg 16 1 L12_B [15:0] $end
$var reg 8 2 L12_addr [7:0] $end
$var reg 4 3 L12_func [3:0] $end
$var reg 4 4 L12_rd [3:0] $end
$var reg 16 5 L23_Z [15:0] $end
$var reg 8 6 L23_addr [7:0] $end
$var reg 4 7 L23_rd [3:0] $end
$var reg 16 8 L34_Z [15:0] $end
$var reg 8 9 L34_addr [7:0] $end
$upscope $end
$upscope $end
$enddefinitions $end
$comment Show the parameter values. $end
$dumpall
$end
#0
$dumpvars
bx 9
bx 8
bx 7
bx 6
bx 5
bx 4
bx 3
bx 2
bx 1
bx 0
b0 /
b0 .
b0 -
b0 ,
b0 +
bx *
b10000 )
b0 (
b0 '
b0 &
b0 %
0$
0#
b0 "
bx !
$end
#10
1#
#12
b0 2
b0 3
b0 4
b1010 1
b1010 0
#15
1$
#20
0#
b10000 "
b10000 +
b110 &
b110 -
b1 (
b1 /
#25
0$
#27
b0 6
b0 7
b10100 5
#30
1#
#32
b0 9
b10100 !
b10100 *
b10100 8
b10000 2
b110 4
b10100 1
#35
1$
#40
0#
b10001 "
b10001 +
b1 %
b1 ,
b111 &
b111 -
b10 (
b10 /
b1 '
b1 .
#45
0$
#47
b10000 6
b110 7
b11110 5
#50
1#
#52
b10001 2
b1 3
b111 4
b101 1
b10100 0
b10000 9
b11110 !
b11110 *
b11110 8
#55
1$
#60
0#
b10010 "
b10010 +
b10 %
b10 ,
b1000 &
b1000 -
b11 (
b11 /
b10 '
b10 .
#65
0$
#67
b10001 6
b111 7
b1111 5
#70
1#
#72
b10001 9
b1111 !
b1111 *
b1111 8
b10010 2
b10 3
b1000 4
b100 1
b101 0
#75
1$
#80
0#
b10011 "
b10011 +
b101 %
b101 ,
b1001 &
b1001 -
b101 (
b101 /
b100 '
b100 .
#85
0$
#87
b10010 6
b1000 7
b10100 5
#90
1#
#92
b10011 2
b101 3
b1001 4
b1000 1
b1111 0
b10010 9
b10100 !
b10100 *
b10100 8
#95
1$
#100
0#
b10100 "
b10100 +
b110 %
b110 ,
b1010 &
b1010 -
#105
0$
#107
b10011 6
b1001 7
b1000 5
#110
1#
#112
b10011 9
b1000 !
b1000 *
b1000 8
b10100 2
b110 3
b1010 4
#115
1$
#120
0#
b10101 "
b10101 +
b111 %
b111 ,
b1011 &
b1011 -
#125
0$
#127
b10100 6
b1010 7
b1111 5
#130
1#
#132
b10101 2
b111 3
b1011 4
b10100 9
b1111 !
b1111 *
b1111 8
#135
1$
#140
0#
b10110 "
b10110 +
b1000 %
b1000 ,
b1100 &
b1100 -
b0 (
b0 /
b10 '
b10 .
#145
0$
#147
b10101 6
b1011 7
b111 5
#150
1#
#152
b10101 9
b111 !
b111 *
b111 8
b10110 2
b1000 3
b1100 4
b10100 1
b101 0
#155
1$
#160
0#
b10111 "
b10111 +
b1010 %
b1010 ,
b1101 &
b1101 -
b100 '
b100 .
#165
0$
#167
b10110 6
b1100 7
b1111111111111011 5
#170
1#
#172
b10111 2
b1010 3
b1101 4
b1111 0
b10110 9
b1111111111111011 !
b1111111111111011 *
b1111111111111011 8
#175
1$
#180
0#
b11000 "
b11000 +
b1011 %
b1011 ,
b1110 &
b1110 -
b10 '
b10 .
#185
0$
#187
b10111 6
b1101 7
b111 5
#190
1#
#192
b10111 9
b111 !
b111 *
b111 8
b11000 2
b1011 3
b1110 4
b101 0
#195
1$
#200
0#
#205
0$
#207
b11000 6
b1110 7
b1010 5
#210
1#
#212
b11000 9
b1010 !
b1010 *
b1010 8
